{
  "metadata_schema_version": 2,
  "fixture_id": "amex_card_statement_20260524_to_20260623",
  "fixture_class": "source-faithful sanitized fixture",
  "sanitization_method": {
    "classification": "clean_room_pdf_reconstruction",
    "source_page_objects_reused": false,
    "source_content_streams_reused": false,
    "source_images_reused": false,
    "source_fonts_reused": false,
    "source_metadata_reused": false,
    "source_annotations_reused": false
  },
  "institution": "American Express",
  "document_family": "card_statement",
  "source_formats": [
    "pdf"
  ],
  "layout_version": "AMEX-CARD-PDF-CLEANROOM-v1",
  "statement_period": {
    "start": "2026-05-24",
    "end": "2026-06-23"
  },
  "statement_date": "2026-06-23",
  "payment_due_date": "2026-07-18",
  "statement_currency": "QAR",
  "transaction_count": 34,
  "instrument_section_count": 1,
  "canonical_ordered_transactions": [
    {
      "source_order": 1,
      "transaction_date": "25-May-2026",
      "posting_date": "26-May-2026",
      "fictional_instrument_identity": null,
      "posted_amount": "5451.00",
      "statement_currency": "QAR",
      "financial_effect": "decreases_amount_owed",
      "source_classification": "payment",
      "sanitized_narration": "PAYMENT RECEIVED ACCOUNT-001 REF-R2-001",
      "original_merchant_amount": null,
      "original_merchant_currency": null,
      "source_conversion_rate": null,
      "markup": null,
      "fee": null,
      "tax": null,
      "page": 1,
      "section": "account_level"
    },
    {
      "source_order": 2,
      "transaction_date": "23-May-2026",
      "posting_date": "24-May-2026",
      "fictional_instrument_identity": "amex-fixture-instrument-001",
      "posted_amount": "34.59",
      "statement_currency": "QAR",
      "financial_effect": "increases_amount_owed",
      "source_classification": "purchase",
      "sanitized_narration": "PURCHASE MERCHANT-038 REF-R2-002",
      "original_merchant_amount": null,
      "original_merchant_currency": null,
      "source_conversion_rate": null,
      "markup": null,
      "fee": null,
      "tax": null,
      "page": 1,
      "section": "instrument_001"
    },
    {
      "source_order": 3,
      "transaction_date": "23-May-2026",
      "posting_date": "25-May-2026",
      "fictional_instrument_identity": "amex-fixture-instrument-001",
      "posted_amount": "29.48",
      "statement_currency": "QAR",
      "financial_effect": "increases_amount_owed",
      "source_classification": "purchase",
      "sanitized_narration": "PURCHASE MERCHANT-038 REF-R2-003",
      "original_merchant_amount": null,
      "original_merchant_currency": null,
      "source_conversion_rate": null,
      "markup": null,
      "fee": null,
      "tax": null,
      "page": 1,
      "section": "instrument_001"
    },
    {
      "source_order": 4,
      "transaction_date": "24-May-2026",
      "posting_date": "26-May-2026",
      "fictional_instrument_identity": "amex-fixture-instrument-001",
      "posted_amount": "184.00",
      "statement_currency": "QAR",
      "financial_effect": "increases_amount_owed",
      "source_classification": "purchase",
      "sanitized_narration": "PURCHASE MERCHANT-043 REF-R2-004",
      "original_merchant_amount": null,
      "original_merchant_currency": null,
      "source_conversion_rate": null,
      "markup": null,
      "fee": null,
      "tax": null,
      "page": 1,
      "section": "instrument_001"
    },
    {
      "source_order": 5,
      "transaction_date": "24-May-2026",
      "posting_date": "25-May-2026",
      "fictional_instrument_identity": "amex-fixture-instrument-001",
      "posted_amount": "36.00",
      "statement_currency": "QAR",
      "financial_effect": "increases_amount_owed",
      "source_classification": "purchase",
      "sanitized_narration": "PURCHASE MERCHANT-038 REF-R2-005",
      "original_merchant_amount": null,
      "original_merchant_currency": null,
      "source_conversion_rate": null,
      "markup": null,
      "fee": null,
      "tax": null,
      "page": 1,
      "section": "instrument_001"
    },
    {
      "source_order": 6,
      "transaction_date": "24-May-2026",
      "posting_date": "26-May-2026",
      "fictional_instrument_identity": "amex-fixture-instrument-001",
      "posted_amount": "31.31",
      "statement_currency": "QAR",
      "financial_effect": "increases_amount_owed",
      "source_classification": "purchase",
      "sanitized_narration": "PURCHASE MERCHANT-038 REF-R2-006",
      "original_merchant_amount": null,
      "original_merchant_currency": null,
      "source_conversion_rate": null,
      "markup": null,
      "fee": null,
      "tax": null,
      "page": 1,
      "section": "instrument_001"
    },
    {
      "source_order": 7,
      "transaction_date": "26-May-2026",
      "posting_date": "27-May-2026",
      "fictional_instrument_identity": "amex-fixture-instrument-001",
      "posted_amount": "54.42",
      "statement_currency": "QAR",
      "financial_effect": "increases_amount_owed",
      "source_classification": "purchase",
      "sanitized_narration": "PURCHASE MERCHANT-038 REF-R2-007",
      "original_merchant_amount": null,
      "original_merchant_currency": null,
      "source_conversion_rate": null,
      "markup": null,
      "fee": null,
      "tax": null,
      "page": 1,
      "section": "instrument_001"
    },
    {
      "source_order": 8,
      "transaction_date": "27-May-2026",
      "posting_date": "29-May-2026",
      "fictional_instrument_identity": "amex-fixture-instrument-001",
      "posted_amount": "282.85",
      "statement_currency": "QAR",
      "financial_effect": "increases_amount_owed",
      "source_classification": "foreign-currency transaction",
      "sanitized_narration": "FOREIGN PURCHASE MERCHANT-045 REF-R2-008",
      "original_merchant_amount": "113475",
      "original_merchant_currency": "KRW",
      "source_conversion_rate": null,
      "markup": null,
      "fee": null,
      "tax": null,
      "page": 1,
      "section": "instrument_001"
    },
    {
      "source_order": 9,
      "transaction_date": "27-May-2026",
      "posting_date": "29-May-2026",
      "fictional_instrument_identity": "amex-fixture-instrument-001",
      "posted_amount": "198.92",
      "statement_currency": "QAR",
      "financial_effect": "increases_amount_owed",
      "source_classification": "foreign-currency transaction",
      "sanitized_narration": "FOREIGN PURCHASE MERCHANT-046 REF-R2-009",
      "original_merchant_amount": "79800",
      "original_merchant_currency": "KRW",
      "source_conversion_rate": null,
      "markup": null,
      "fee": null,
      "tax": null,
      "page": 1,
      "section": "instrument_001"
    },
    {
      "source_order": 10,
      "transaction_date": "27-May-2026",
      "posting_date": "29-May-2026",
      "fictional_instrument_identity": "amex-fixture-instrument-001",
      "posted_amount": "39.03",
      "statement_currency": "QAR",
      "financial_effect": "increases_amount_owed",
      "source_classification": "foreign-currency transaction",
      "sanitized_narration": "FOREIGN PURCHASE MERCHANT-047 REF-R2-010",
      "original_merchant_amount": "15660",
      "original_merchant_currency": "KRW",
      "source_conversion_rate": null,
      "markup": null,
      "fee": null,
      "tax": null,
      "page": 1,
      "section": "instrument_001"
    },
    {
      "source_order": 11,
      "transaction_date": "27-May-2026",
      "posting_date": "30-May-2026",
      "fictional_instrument_identity": "amex-fixture-instrument-001",
      "posted_amount": "400.87",
      "statement_currency": "QAR",
      "financial_effect": "increases_amount_owed",
      "source_classification": "foreign-currency transaction",
      "sanitized_narration": "FOREIGN PURCHASE MERCHANT-048 REF-R2-011",
      "original_merchant_amount": "161000",
      "original_merchant_currency": "KRW",
      "source_conversion_rate": null,
      "markup": null,
      "fee": null,
      "tax": null,
      "page": 1,
      "section": "instrument_001"
    },
    {
      "source_order": 12,
      "transaction_date": "27-May-2026",
      "posting_date": "30-May-2026",
      "fictional_instrument_identity": "amex-fixture-instrument-001",
      "posted_amount": "25.41",
      "statement_currency": "QAR",
      "financial_effect": "increases_amount_owed",
      "source_classification": "foreign-currency transaction",
      "sanitized_narration": "FOREIGN PURCHASE MERCHANT-049 REF-R2-012",
      "original_merchant_amount": "10200",
      "original_merchant_currency": "KRW",
      "source_conversion_rate": null,
      "markup": null,
      "fee": null,
      "tax": null,
      "page": 1,
      "section": "instrument_001"
    },
    {
      "source_order": 13,
      "transaction_date": "27-May-2026",
      "posting_date": "28-May-2026",
      "fictional_instrument_identity": "amex-fixture-instrument-001",
      "posted_amount": "5.13",
      "statement_currency": "QAR",
      "financial_effect": "increases_amount_owed",
      "source_classification": "foreign-currency transaction",
      "sanitized_narration": "FOREIGN PURCHASE MERCHANT-050 REF-R2-013",
      "original_merchant_amount": "130.64",
      "original_merchant_currency": "INR",
      "source_conversion_rate": null,
      "markup": null,
      "fee": null,
      "tax": null,
      "page": 1,
      "section": "instrument_001"
    },
    {
      "source_order": 14,
      "transaction_date": "28-May-2026",
      "posting_date": "31-May-2026",
      "fictional_instrument_identity": "amex-fixture-instrument-001",
      "posted_amount": "100.00",
      "statement_currency": "QAR",
      "financial_effect": "increases_amount_owed",
      "source_classification": "purchase",
      "sanitized_narration": "PURCHASE MERCHANT-051 REF-R2-014",
      "original_merchant_amount": null,
      "original_merchant_currency": null,
      "source_conversion_rate": null,
      "markup": null,
      "fee": null,
      "tax": null,
      "page": 1,
      "section": "instrument_001"
    },
    {
      "source_order": 15,
      "transaction_date": "28-May-2026",
      "posting_date": "01-Jun-2026",
      "fictional_instrument_identity": "amex-fixture-instrument-001",
      "posted_amount": "61.00",
      "statement_currency": "QAR",
      "financial_effect": "increases_amount_owed",
      "source_classification": "purchase",
      "sanitized_narration": "PURCHASE MERCHANT-037 REF-R2-015",
      "original_merchant_amount": null,
      "original_merchant_currency": null,
      "source_conversion_rate": null,
      "markup": null,
      "fee": null,
      "tax": null,
      "page": 1,
      "section": "instrument_001"
    },
    {
      "source_order": 16,
      "transaction_date": "28-May-2026",
      "posting_date": "01-Jun-2026",
      "fictional_instrument_identity": "amex-fixture-instrument-001",
      "posted_amount": "32.00",
      "statement_currency": "QAR",
      "financial_effect": "increases_amount_owed",
      "source_classification": "purchase",
      "sanitized_narration": "PURCHASE MERCHANT-042 REF-R2-016",
      "original_merchant_amount": null,
      "original_merchant_currency": null,
      "source_conversion_rate": null,
      "markup": null,
      "fee": null,
      "tax": null,
      "page": 2,
      "section": "instrument_001"
    },
    {
      "source_order": 17,
      "transaction_date": "29-May-2026",
      "posting_date": "01-Jun-2026",
      "fictional_instrument_identity": "amex-fixture-instrument-001",
      "posted_amount": "177.18",
      "statement_currency": "QAR",
      "financial_effect": "increases_amount_owed",
      "source_classification": "purchase",
      "sanitized_narration": "PURCHASE MERCHANT-052 REF-R2-017",
      "original_merchant_amount": null,
      "original_merchant_currency": null,
      "source_conversion_rate": null,
      "markup": null,
      "fee": null,
      "tax": null,
      "page": 2,
      "section": "instrument_001"
    },
    {
      "source_order": 18,
      "transaction_date": "29-May-2026",
      "posting_date": "01-Jun-2026",
      "fictional_instrument_identity": "amex-fixture-instrument-001",
      "posted_amount": "10.00",
      "statement_currency": "QAR",
      "financial_effect": "increases_amount_owed",
      "source_classification": "purchase",
      "sanitized_narration": "PURCHASE MERCHANT-053 REF-R2-018",
      "original_merchant_amount": null,
      "original_merchant_currency": null,
      "source_conversion_rate": null,
      "markup": null,
      "fee": null,
      "tax": null,
      "page": 2,
      "section": "instrument_001"
    },
    {
      "source_order": 19,
      "transaction_date": "29-May-2026",
      "posting_date": "31-May-2026",
      "fictional_instrument_identity": "amex-fixture-instrument-001",
      "posted_amount": "17.82",
      "statement_currency": "QAR",
      "financial_effect": "increases_amount_owed",
      "source_classification": "purchase",
      "sanitized_narration": "PURCHASE MERCHANT-038 REF-R2-019",
      "original_merchant_amount": null,
      "original_merchant_currency": null,
      "source_conversion_rate": null,
      "markup": null,
      "fee": null,
      "tax": null,
      "page": 2,
      "section": "instrument_001"
    },
    {
      "source_order": 20,
      "transaction_date": "29-May-2026",
      "posting_date": "30-May-2026",
      "fictional_instrument_identity": "amex-fixture-instrument-001",
      "posted_amount": "21.51",
      "statement_currency": "QAR",
      "financial_effect": "increases_amount_owed",
      "source_classification": "purchase",
      "sanitized_narration": "PURCHASE MERCHANT-038 REF-R2-020",
      "original_merchant_amount": null,
      "original_merchant_currency": null,
      "source_conversion_rate": null,
      "markup": null,
      "fee": null,
      "tax": null,
      "page": 2,
      "section": "instrument_001"
    },
    {
      "source_order": 21,
      "transaction_date": "29-May-2026",
      "posting_date": "30-May-2026",
      "fictional_instrument_identity": "amex-fixture-instrument-001",
      "posted_amount": "15.25",
      "statement_currency": "QAR",
      "financial_effect": "increases_amount_owed",
      "source_classification": "purchase",
      "sanitized_narration": "PURCHASE MERCHANT-038 REF-R2-021",
      "original_merchant_amount": null,
      "original_merchant_currency": null,
      "source_conversion_rate": null,
      "markup": null,
      "fee": null,
      "tax": null,
      "page": 2,
      "section": "instrument_001"
    },
    {
      "source_order": 22,
      "transaction_date": "29-May-2026",
      "posting_date": "30-May-2026",
      "fictional_instrument_identity": "amex-fixture-instrument-001",
      "posted_amount": "31.41",
      "statement_currency": "QAR",
      "financial_effect": "increases_amount_owed",
      "source_classification": "purchase",
      "sanitized_narration": "PURCHASE MERCHANT-038 REF-R2-022",
      "original_merchant_amount": null,
      "original_merchant_currency": null,
      "source_conversion_rate": null,
      "markup": null,
      "fee": null,
      "tax": null,
      "page": 2,
      "section": "instrument_001"
    },
    {
      "source_order": 23,
      "transaction_date": "30-May-2026",
      "posting_date": "01-Jun-2026",
      "fictional_instrument_identity": "amex-fixture-instrument-001",
      "posted_amount": "23.00",
      "statement_currency": "QAR",
      "financial_effect": "increases_amount_owed",
      "source_classification": "purchase",
      "sanitized_narration": "PURCHASE MERCHANT-043 REF-R2-023",
      "original_merchant_amount": null,
      "original_merchant_currency": null,
      "source_conversion_rate": null,
      "markup": null,
      "fee": null,
      "tax": null,
      "page": 2,
      "section": "instrument_001"
    },
    {
      "source_order": 24,
      "transaction_date": "30-May-2026",
      "posting_date": "31-May-2026",
      "fictional_instrument_identity": "amex-fixture-instrument-001",
      "posted_amount": "7.42",
      "statement_currency": "QAR",
      "financial_effect": "increases_amount_owed",
      "source_classification": "purchase",
      "sanitized_narration": "PURCHASE MERCHANT-038 REF-R2-024",
      "original_merchant_amount": null,
      "original_merchant_currency": null,
      "source_conversion_rate": null,
      "markup": null,
      "fee": null,
      "tax": null,
      "page": 2,
      "section": "instrument_001"
    },
    {
      "source_order": 25,
      "transaction_date": "30-May-2026",
      "posting_date": "31-May-2026",
      "fictional_instrument_identity": "amex-fixture-instrument-001",
      "posted_amount": "13.39",
      "statement_currency": "QAR",
      "financial_effect": "increases_amount_owed",
      "source_classification": "purchase",
      "sanitized_narration": "PURCHASE MERCHANT-038 REF-R2-025",
      "original_merchant_amount": null,
      "original_merchant_currency": null,
      "source_conversion_rate": null,
      "markup": null,
      "fee": null,
      "tax": null,
      "page": 2,
      "section": "instrument_001"
    },
    {
      "source_order": 26,
      "transaction_date": "31-May-2026",
      "posting_date": "01-Jun-2026",
      "fictional_instrument_identity": "amex-fixture-instrument-001",
      "posted_amount": "61.01",
      "statement_currency": "QAR",
      "financial_effect": "increases_amount_owed",
      "source_classification": "purchase",
      "sanitized_narration": "PURCHASE MERCHANT-038 REF-R2-026",
      "original_merchant_amount": null,
      "original_merchant_currency": null,
      "source_conversion_rate": null,
      "markup": null,
      "fee": null,
      "tax": null,
      "page": 2,
      "section": "instrument_001"
    },
    {
      "source_order": 27,
      "transaction_date": "01-Jun-2026",
      "posting_date": "02-Jun-2026",
      "fictional_instrument_identity": "amex-fixture-instrument-001",
      "posted_amount": "41.00",
      "statement_currency": "QAR",
      "financial_effect": "increases_amount_owed",
      "source_classification": "purchase",
      "sanitized_narration": "PURCHASE MERCHANT-037 REF-R2-027",
      "original_merchant_amount": null,
      "original_merchant_currency": null,
      "source_conversion_rate": null,
      "markup": null,
      "fee": null,
      "tax": null,
      "page": 2,
      "section": "instrument_001"
    },
    {
      "source_order": 28,
      "transaction_date": "01-Jun-2026",
      "posting_date": "02-Jun-2026",
      "fictional_instrument_identity": "amex-fixture-instrument-001",
      "posted_amount": "393.25",
      "statement_currency": "QAR",
      "financial_effect": "increases_amount_owed",
      "source_classification": "purchase",
      "sanitized_narration": "PURCHASE MERCHANT-041 REF-R2-028",
      "original_merchant_amount": null,
      "original_merchant_currency": null,
      "source_conversion_rate": null,
      "markup": null,
      "fee": null,
      "tax": null,
      "page": 2,
      "section": "instrument_001"
    },
    {
      "source_order": 29,
      "transaction_date": "02-Jun-2026",
      "posting_date": "03-Jun-2026",
      "fictional_instrument_identity": "amex-fixture-instrument-001",
      "posted_amount": "2586.53",
      "statement_currency": "QAR",
      "financial_effect": "increases_amount_owed",
      "source_classification": "foreign-currency transaction",
      "sanitized_narration": "FOREIGN PURCHASE MERCHANT-002 REF-R2-029",
      "original_merchant_amount": "691.23",
      "original_merchant_currency": "USD",
      "source_conversion_rate": null,
      "markup": null,
      "fee": null,
      "tax": null,
      "page": 2,
      "section": "instrument_001"
    },
    {
      "source_order": 30,
      "transaction_date": "03-Jun-2026",
      "posting_date": "04-Jun-2026",
      "fictional_instrument_identity": "amex-fixture-instrument-001",
      "posted_amount": "2821.41",
      "statement_currency": "QAR",
      "financial_effect": "increases_amount_owed",
      "source_classification": "foreign-currency transaction",
      "sanitized_narration": "FOREIGN PURCHASE MERCHANT-054 REF-R2-030",
      "original_merchant_amount": "754.00",
      "original_merchant_currency": "USD",
      "source_conversion_rate": null,
      "markup": null,
      "fee": null,
      "tax": null,
      "page": 2,
      "section": "instrument_001"
    },
    {
      "source_order": 31,
      "transaction_date": "03-Jun-2026",
      "posting_date": "04-Jun-2026",
      "fictional_instrument_identity": "amex-fixture-instrument-001",
      "posted_amount": "2586.53",
      "statement_currency": "QAR",
      "financial_effect": "decreases_amount_owed",
      "source_classification": "refund",
      "sanitized_narration": "REFUND MERCHANT-002 REF-R2-031",
      "original_merchant_amount": "691.23",
      "original_merchant_currency": "USD",
      "source_conversion_rate": null,
      "markup": null,
      "fee": null,
      "tax": null,
      "page": 2,
      "section": "instrument_001"
    },
    {
      "source_order": 32,
      "transaction_date": "17-Jun-2026",
      "posting_date": "21-Jun-2026",
      "fictional_instrument_identity": "amex-fixture-instrument-001",
      "posted_amount": "193.20",
      "statement_currency": "QAR",
      "financial_effect": "increases_amount_owed",
      "source_classification": "purchase",
      "sanitized_narration": "PURCHASE MERCHANT-043 REF-R2-032",
      "original_merchant_amount": null,
      "original_merchant_currency": null,
      "source_conversion_rate": null,
      "markup": null,
      "fee": null,
      "tax": null,
      "page": 2,
      "section": "instrument_001"
    },
    {
      "source_order": 33,
      "transaction_date": "18-Jun-2026",
      "posting_date": "21-Jun-2026",
      "fictional_instrument_identity": "amex-fixture-instrument-001",
      "posted_amount": "78.56",
      "statement_currency": "QAR",
      "financial_effect": "increases_amount_owed",
      "source_classification": "purchase",
      "sanitized_narration": "PURCHASE MERCHANT-043 REF-R2-033",
      "original_merchant_amount": null,
      "original_merchant_currency": null,
      "source_conversion_rate": null,
      "markup": null,
      "fee": null,
      "tax": null,
      "page": 2,
      "section": "instrument_001"
    },
    {
      "source_order": 34,
      "transaction_date": "18-Jun-2026",
      "posting_date": "19-Jun-2026",
      "fictional_instrument_identity": "amex-fixture-instrument-001",
      "posted_amount": "2342.18",
      "statement_currency": "QAR",
      "financial_effect": "increases_amount_owed",
      "source_classification": "foreign-currency transaction",
      "sanitized_narration": "FOREIGN PURCHASE MERCHANT-055 REF-R2-034",
      "original_merchant_amount": "1074.56",
      "original_merchant_currency": "NZD",
      "source_conversion_rate": null,
      "markup": null,
      "fee": null,
      "tax": null,
      "page": 3,
      "section": "instrument_001"
    }
  ],
  "observed_statement_summary": {
    "previous_balance": "5450.28",
    "payments_and_credits_total": "8037.53",
    "new_debits_total": "10349.13",
    "statement_closing_balance": "7761.88",
    "minimum_payment_due": null,
    "full_payment_due": null,
    "cash_advance_total": null,
    "fees_total": null,
    "interest_or_finance_charge_total": null,
    "credit_or_spending_limit": null,
    "available_credit": null,
    "rewards_summary": {
      "period": "2026-05-23 to 2026-06-23",
      "opening": 24281,
      "new": 1379,
      "closing": 25660
    },
    "reconciliation_rule": "previous_balance - new_credits + new_debits = new_balance",
    "reconciles": true,
    "source_defined_exclusions": []
  },
  "fictional_customer_identity": "amex-fixture-customer-001",
  "fictional_account_identity": "amex-fixture-account-001",
  "fictional_instrument_identities": [
    "amex-fixture-instrument-001"
  ],
  "validation_expectation": "expected evidence-valid; no production card semantics implied",
  "source_text_boundary": "Private identity, merchant, card and reference values are replaced; financial, currency, FX and structure evidence is exact.",
  "ocr_boundary": {
    "native_text_available": true,
    "pdfkit_extraction_usable": true,
    "pymupdf_extraction_usable": true,
    "ocr_used": false,
    "ocr_required_for_fixture": false,
    "scope": "approved_fixture_layout_only"
  },
  "period_relationship": {
    "chronology": "R1 then R2",
    "overlap": "none",
    "calendar_relationship": "contiguous"
  },
  "account_relationship": "same fictional account across both periods based on source continuity",
  "instrument_relationship": "same fictional instrument section across both periods based on source continuity",
  "layout_relationship": "same observed layout version across both periods",
  "production_support_boundary": "fixture evidence only; does not define card-domain semantics or establish production support"
}
